{"features": [{"properties": {"adminCode1": "83", "fcode": "PPL", "lng": "41.6295", "toponymName": "Melenki", "population": 15902, "name": "Melenki", "lat": "55.3343", "fcodeName": "populated place", "fclName": "city, village,...", "countryName": "Russia", "adminName1": "Vladimir", "countryId": "2017370", "fcl": "P", "geonameId": 527740, "countryCode": "RU"}, "geometry": {"coordinates": [41.6295, 55.3343], "type": "Point"}, "type": "Feature"}, {"properties": {"adminCode1": "51", "fcode": "PPL", "lng": "42.9855", "toponymName": "Melenki", "population": 0, "name": "Melenki", "lat": "55.9436", "fcodeName": "populated place", "fclName": "city, village,...", "countryName": "Russia", "adminName1": "Nizjnij Novgorod", "countryId": "2017370", "fcl": "P", "geonameId": 527739, "countryCode": "RU"}, "geometry": {"coordinates": [42.9855, 55.9436], "type": "Point"}, "type": "Feature"}], "type": "FeatureCollection"}