{"features": [{"properties": {"adminCode1": "54", "fcode": "PPLA", "lng": "73.36859", "toponymName": "Omsk", "population": 1129281, "name": "Omsk", "lat": "54.99244", "fcodeName": "seat of a first-order administrative division", "fclName": "city, village,...", "countryName": "Russia", "adminName1": "Omsk", "countryId": "2017370", "fcl": "P", "geonameId": 1496153, "countryCode": "RU"}, "geometry": {"coordinates": [73.36859, 54.99244], "type": "Point"}, "type": "Feature"}], "type": "FeatureCollection"}