{"features": [{"properties": {"adminCode1": "11", "fcode": "PPLA", "lng": "34.11079", "toponymName": "Simferopol", "population": 358108, "name": "Simferopol", "lat": "44.95719", "fcodeName": "seat of a first-order administrative division", "fclName": "city, village,...", "countryName": "Ukraine", "adminName1": "Crimea", "countryId": "690791", "fcl": "P", "geonameId": 693805, "countryCode": "UA"}, "geometry": {"coordinates": [34.11079, 44.95719], "type": "Point"}, "type": "Feature"}, {"properties": {"adminCode1": "13", "fcode": "PPL", "lng": "65.36653", "toponymName": "Simferopol\u2019", "population": 0, "name": "Simferopol'", "lat": "52.43458", "fcodeName": "populated place", "fclName": "city, village,...", "countryName": "Kazakhstan", "adminName1": "Qostanay", "countryId": "1522867", "fcl": "P", "geonameId": 1521680, "countryCode": "KZ"}, "geometry": {"coordinates": [65.36653, 52.43458], "type": "Point"}, "type": "Feature"}, {"properties": {"adminCode1": "16", "fcode": "PPL", "lng": "69.02827", "toponymName": "Simferopol\u2019skoye", "population": 0, "name": "Simferopol'skoye", "lat": "53.33719", "fcodeName": "populated place", "fclName": "city, village,...", "countryName": "Kazakhstan", "adminName1": "Solt\u00fcstik Qazaqstan", "countryId": "1522867", "fcl": "P", "geonameId": 1518969, "countryCode": "KZ"}, "geometry": {"coordinates": [69.02827, 53.33719], "type": "Point"}, "type": "Feature"}], "type": "FeatureCollection"}