{"features": [{"properties": {"adminCode1": "46", "fcode": "PPL", "lng": "46.02559", "toponymName": "Tetyushi", "population": 0, "name": "Tetyushi", "lat": "54.57112", "fcodeName": "populated place", "fclName": "city, village,...", "countryName": "Russia", "adminName1": "Mordoviya", "countryId": "2017370", "fcl": "P", "geonameId": 483151, "countryCode": "RU"}, "geometry": {"coordinates": [46.02559, 54.57112], "type": "Point"}, "type": "Feature"}, {"properties": {"adminCode1": "73", "fcode": "PPL", "lng": "48.83656", "toponymName": "Tetyushi", "population": 11826, "name": "Tetyushi", "lat": "54.93821", "fcodeName": "populated place", "fclName": "city, village,...", "countryName": "Russia", "adminName1": "Tatarstan", "countryId": "2017370", "fcl": "P", "geonameId": 483150, "countryCode": "RU"}, "geometry": {"coordinates": [48.83656, 54.93821], "type": "Point"}, "type": "Feature"}], "type": "FeatureCollection"}